nonebot_plugin_giyf/__init__.py
nonebot_plugin_giyf/config.py
nonebot_plugin_giyf/config_manager.py
nonebot_plugin_giyf/data_source.py
nonebot_plugin_giyf-0.1.3.dist-info/LICENSE
nonebot_plugin_giyf-0.1.3.dist-info/WHEEL
nonebot_plugin_giyf-0.1.3.dist-info/METADATA
nonebot_plugin_giyf-0.1.3.dist-info/RECORD
