Metadata-Version: 2.1
Name: nonebot-plugin-giyf
Version: 0.1.3
Summary: nonebot2 群聊快速生成搜索引擎链接
Home-page: https://github.com/KoishiMoe/nonebot-plugin-giyf
License: AGPL-3.0-or-later
Author: KoishiMoe
Author-email: 68314080+KoishiMoe@users.noreply.github.com
Requires-Python: >=3.7.3,<4.0.0
Classifier: License :: OSI Approved :: GNU Affero General Public License v3 or later (AGPLv3+)
Classifier: Programming Language :: Python :: 3
Classifier: Programming Language :: Python :: 3.10
Classifier: Programming Language :: Python :: 3.8
Classifier: Programming Language :: Python :: 3.9
Requires-Dist: nonebot-adapter-onebot (>=2.1.0,<2.2.0)
Requires-Dist: nonebot2 (>=2.0.0b2,<2.1.0)
Project-URL: Repository, https://github.com/KoishiMoe/nonebot-plugin-giyf
